mistral_ocr/__init__.py
mistral_ocr/cli.py
mistral_ocr-0.5.0.dist-info/METADATA
mistral_ocr-0.5.0.dist-info/WHEEL
mistral_ocr-0.5.0.dist-info/entry_points.txt
mistral_ocr-0.5.0.dist-info/top_level.txt
mistral_ocr-0.5.0.dist-info/RECORD
