Metadata-Version: 2.2
Name: mistral-ocr
Version: 0.5.0
Summary: A tool for OCR using Mistral. Ensure your MISTRAL_API_KEY is exported or in ~/.zshrc or ~/.bashrc
Author-email: Elliot Arledge <your.email@example.com>
Project-URL: Homepage, https://github.com/yourusername/mistral-ocr
Project-URL: Bug Tracker, https://github.com/yourusername/mistral-ocr/issues
Classifier: Programming Language :: Python :: 3
Classifier: License :: OSI Approved :: MIT License
Classifier: Operating System :: OS Independent
Requires-Python: >=3.8
Requires-Dist: mistralai>=1.5.1
Requires-Dist: python-dotenv>=1.0.1
